pimp/__init__.py
pimplife-0.1.4.dist-info/LICENSE
pimplife-0.1.4.dist-info/METADATA
pimplife-0.1.4.dist-info/WHEEL
pimplife-0.1.4.dist-info/entry_points.txt
pimplife-0.1.4.dist-info/RECORD
